sip_videogen/__init__.py
sip_videogen/__main__.py
sip_videogen/cli.py
sip_videogen/exceptions.py
sip_videogen/agents/__init__.py
sip_videogen/agents/brand_designer.py
sip_videogen/agents/continuity_supervisor.py
sip_videogen/agents/image_reviewer.py
sip_videogen/agents/music_director.py
sip_videogen/agents/production_designer.py
sip_videogen/agents/prompt_repair.py
sip_videogen/agents/screenwriter.py
sip_videogen/agents/showrunner.py
sip_videogen/agents/prompts/__init__.py
sip_videogen/agents/prompts/brand_designer.md
sip_videogen/agents/prompts/continuity_supervisor.md
sip_videogen/agents/prompts/image_reviewer.md
sip_videogen/agents/prompts/music_director.md
sip_videogen/agents/prompts/production_designer.md
sip_videogen/agents/prompts/prompt_repair.md
sip_videogen/agents/prompts/screenwriter.md
sip_videogen/agents/prompts/showrunner.md
sip_videogen/agents/tools/__init__.py
sip_videogen/agents/tools/image_production.py
sip_videogen/assembler/__init__.py
sip_videogen/assembler/ffmpeg.py
sip_videogen/brand_kit/__init__.py
sip_videogen/brand_kit/workflow.py
sip_videogen/config/__init__.py
sip_videogen/config/costs.py
sip_videogen/config/logging.py
sip_videogen/config/settings.py
sip_videogen/config/setup.py
sip_videogen/config/user_preferences.py
sip_videogen/generators/__init__.py
sip_videogen/generators/base.py
sip_videogen/generators/factory.py
sip_videogen/generators/image_generator.py
sip_videogen/generators/kling_generator.py
sip_videogen/generators/music_generator.py
sip_videogen/generators/nano_banana_generator.py
sip_videogen/generators/prompt_builder.py
sip_videogen/generators/video_generator.py
sip_videogen/models/__init__.py
sip_videogen/models/agent_outputs.py
sip_videogen/models/assets.py
sip_videogen/models/brand_kit.py
sip_videogen/models/image_review.py
sip_videogen/models/music.py
sip_videogen/models/script.py
sip_videogen/utils/__init__.py
sip_videogen/utils/updater.py
sip_videogen-0.4.4.dist-info/METADATA
sip_videogen-0.4.4.dist-info/WHEEL
sip_videogen-0.4.4.dist-info/entry_points.txt
sip_videogen-0.4.4.dist-info/RECORD
