Metadata-Version: 2.4
Name: sip-videogen
Version: 0.4.4
Summary: Transform video ideas into complete videos using AI agent teams
Project-URL: Homepage, https://github.com/chufeng-huang-sipaway/sip-videogen
Project-URL: Repository, https://github.com/chufeng-huang-sipaway/sip-videogen
Author: Sip Team
License: MIT
Classifier: Development Status :: 4 - Beta
Classifier: Environment :: Console
Classifier: Intended Audience :: Developers
Classifier: License :: OSI Approved :: MIT License
Classifier: Operating System :: OS Independent
Classifier: Programming Language :: Python :: 3
Classifier: Programming Language :: Python :: 3.11
Classifier: Programming Language :: Python :: 3.12
Classifier: Topic :: Multimedia :: Video
Classifier: Topic :: Scientific/Engineering :: Artificial Intelligence
Requires-Python: >=3.11
Requires-Dist: google-cloud-storage>=2.0.0
Requires-Dist: google-genai>=1.51.0
Requires-Dist: httpx>=0.27.0
Requires-Dist: openai-agents>=0.1.0
Requires-Dist: packaging>=23.0
Requires-Dist: pillow>=10.0.0
Requires-Dist: pydantic-settings>=2.0.0
Requires-Dist: pydantic>=2.0.0
Requires-Dist: pyjwt>=2.8.0
Requires-Dist: python-dotenv>=1.0.0
Requires-Dist: questionary>=2.0.0
Requires-Dist: rich>=13.0.0
Requires-Dist: tenacity>=8.0.0
Requires-Dist: typer[all]>=0.12.0
Provides-Extra: dev
Requires-Dist: build>=1.0.0; extra == 'dev'
Requires-Dist: mypy>=1.0.0; extra == 'dev'
Requires-Dist: pytest-asyncio>=0.23.0; extra == 'dev'
Requires-Dist: pytest>=8.0.0; extra == 'dev'
Requires-Dist: ruff>=0.4.0; extra == 'dev'
Requires-Dist: twine>=5.0.0; extra == 'dev'
